folint/SCA.py
folint/__init__.py
folint/ast_engine/Annotate.py
folint/ast_engine/Assignments.py
folint/ast_engine/Expression.py
folint/ast_engine/Parse.py
folint/ast_engine/Simplify.py
folint/ast_engine/__init__.py
folint/ast_engine/utils.py
folint-1.1.0.dist-info/LICENSE
folint-1.1.0.dist-info/METADATA
folint-1.1.0.dist-info/WHEEL
folint-1.1.0.dist-info/entry_points.txt
folint-1.1.0.dist-info/top_level.txt
folint-1.1.0.dist-info/RECORD
