Metadata-Version: 2.1
Name: folint
Version: 1.1.0
Summary: Linter for FO-dot, used in the IDP-Z3 system
Home-page: https://gitlab.com/EAVISE/sva/folint
Author: vadevesi
Author-email: s.vandevelde@kuleuven.be
Classifier: Topic :: Scientific/Engineering
Classifier: Topic :: Software Development
Classifier: Topic :: Scientific/Engineering :: Artificial Intelligence
Classifier: Topic :: Scientific/Engineering :: Mathematics
Classifier: Topic :: Software Development :: Quality Assurance
License-File: LICENSE
Requires-Dist: idp-engine >=0.11.2
